chips/__init__.py
chips/smbus.py
chips/spi.py
numat_chips-0.1.1.dist-info/LICENSE
numat_chips-0.1.1.dist-info/METADATA
numat_chips-0.1.1.dist-info/WHEEL
numat_chips-0.1.1.dist-info/entry_points.txt
numat_chips-0.1.1.dist-info/top_level.txt
numat_chips-0.1.1.dist-info/RECORD
