Metadata-Version: 2.1
Name: numat-chips
Version: 0.1.1
Summary: Drivers for ADCs, sensors, and other electronic chips.
Home-page: http://github.com/numat/chips/
Author: Patrick Fuller
Author-email: pat@numat-tech.com
License: GPLv3
Platform: UNKNOWN
Classifier: License :: OSI Approved :: GNU General Public License v3 (GPLv3)
Classifier: Development Status :: 4 - Beta
Classifier: Natural Language :: English
Classifier: Programming Language :: Python
Classifier: Programming Language :: Python :: 2
Classifier: Programming Language :: Python :: 3
Classifier: Topic :: Scientific/Engineering :: Interface Engine/Protocol Translator
Requires-Dist: smbus
Requires-Dist: spidev
